pydproc/__init__.py
pydproc/docker_base/Dockerfile
pydproc/docker_base/build.sh
pydproc/docker_base/proc.yml
pydproc/docker_base/run.sh
pydproc/docker_base/run_proc.py
pydproc/scripts/__init__.py
pydproc/scripts/cli.py
pydproc/scripts/definitions.py
pydproc/scripts/utils.py
pydproc/scripts/workflow.py
pydproc-1.1.dist-info/LICENSE.md
pydproc-1.1.dist-info/METADATA
pydproc-1.1.dist-info/WHEEL
pydproc-1.1.dist-info/entry_points.txt
pydproc-1.1.dist-info/top_level.txt
pydproc-1.1.dist-info/RECORD
