Metadata-Version: 2.1
Name: pydproc
Version: 1.1
Summary: A useful module
Home-page: https://github.com/vladov3000/pydproc
Author: Vladimir Oveckin, Robert Burris, Andrew Wu
Author-email: vladov3000@gmail.com
License: MIT
Platform: UNKNOWN
Requires-Dist: pyyaml
Requires-Dist: click
Requires-Dist: docker
